vierror/Except.py
vierror/MError.py
vierror/__init__.py
vierror/py.typed
vierror-0.0.2.dist-info/METADATA
vierror-0.0.2.dist-info/WHEEL
vierror-0.0.2.dist-info/licenses/LICENSE.txt
vierror-0.0.2.dist-info/RECORD
